flask_iam/__init__.py
flask_iam/models.py
flask_iam/utils.py
flask_iam/templates/IAM/form.html
flask_iam/templates/IAM/index.html
flask_iam/templates/IAM/list.html
flask_iam/templates/IAM/login.html
flask_iam/templates/IAM/nav.html
flask_iam/templates/IAM/registration_success.html
flask_iam-0.0.9.dist-info/licenses/LICENSE
flask_iam-0.0.9.dist-info/METADATA
flask_iam-0.0.9.dist-info/WHEEL
flask_iam-0.0.9.dist-info/top_level.txt
flask_iam-0.0.9.dist-info/RECORD
