Metadata-Version: 2.4
Name: Flask-IAM
Version: 0.0.9
License-File: LICENSE
Requires-Dist: Flask-Login==0.6.3
Requires-Dist: Flask-UXFab>=0.0.1
Requires-Dist: email_validator==2.2.0
Requires-Dist: phonenumbers==8.13.42
Dynamic: license-file
